brutax/__init__.py
brutax/_internal.py
brutax/_loop.py
brutax/_method.py
brutax/_tree_grid.py
brutax/_types.py
brutax/brutax_version.py
brutax-0.0.2.dist-info/METADATA
brutax-0.0.2.dist-info/WHEEL
brutax-0.0.2.dist-info/licenses/LICENSE
brutax-0.0.2.dist-info/RECORD
