Metadata-Version: 2.4
Name: brutax
Version: 0.0.2
Summary: Function minimization by brute force grid search in JAX
Project-URL: repository, https://github.com/michael-0brien/brutax
Author-email: Michael O'Brien <michaelobrien@g.harvard.edu>
License:                                  Apache License
License-File: LICENSE
Keywords: equinox,grid-search,jax,optimization
Classifier: Development Status :: 4 - Beta
Classifier: Intended Audience :: Developers
Classifier: Intended Audience :: Science/Research
Classifier: License :: OSI Approved :: Apache Software License
Classifier: Operating System :: OS Independent
Classifier: Programming Language :: Python
Classifier: Programming Language :: Python :: 3
Requires-Python: >=3.10
Requires-Dist: equinox>=0.11.0
Requires-Dist: jax
Requires-Dist: jaxtyping>=0.2.23
Requires-Dist: tqdm
Provides-Extra: dev
Requires-Dist: pre-commit; extra == 'dev'
Provides-Extra: tests
Requires-Dist: pytest; extra == 'tests'
Requires-Dist: pytest-cov; extra == 'tests'
